nemdatatools/__init__.py
nemdatatools/_version.py
nemdatatools/batch_commands.py
nemdatatools/cache.py
nemdatatools/data_source.py
nemdatatools/downloader.py
nemdatatools/mmsdm_helper.py
nemdatatools/processor.py
nemdatatools/timeutils.py
nemdatatools-0.1.0.dist-info/licenses/LICENSE
nemdatatools-0.1.0.dist-info/METADATA
nemdatatools-0.1.0.dist-info/WHEEL
nemdatatools-0.1.0.dist-info/top_level.txt
nemdatatools-0.1.0.dist-info/RECORD
