Metadata-Version: 2.4
Name: nemdatatools
Version: 0.1.0
Summary: Tools for accessing and preprocessing AEMO data for the National Electricity Market
Author-email: Zhipeng He <zhipeng.he@hdr.qut.edu.au>
License: MIT
Project-URL: Homepage, https://github.com/ZhipengHe/nemdatatools
Project-URL: Documentation, https://zhipenghe.me/nemdatatools/
Project-URL: Bug Tracker, https://github.com/ZhipengHe/nemdatatools/issues
Classifier: Development Status :: 4 - Beta
Classifier: Intended Audience :: Developers
Classifier: Intended Audience :: Science/Research
Classifier: License :: OSI Approved :: MIT License
Classifier: Programming Language :: Python :: 3
Classifier: Programming Language :: Python :: 3.10
Classifier: Programming Language :: Python :: 3.11
Classifier: Programming Language :: Python :: 3.12
Classifier: Programming Language :: Python :: 3.13
Requires-Python: >=3.10
License-File: LICENSE
Requires-Dist: requests>=2.25.0
Requires-Dist: pandas>=1.3.0
Requires-Dist: numpy>=1.20.0
Requires-Dist: pyarrow>=19.0.0
Requires-Dist: tqdm>=4.0.0
Provides-Extra: dev
Requires-Dist: pytest>=6.0; extra == "dev"
Requires-Dist: pytest-cov>=2.12; extra == "dev"
Requires-Dist: black>=25.0.0; extra == "dev"
Requires-Dist: mypy>=1.14.0; extra == "dev"
Requires-Dist: types-requests>=2.32.0; extra == "dev"
Requires-Dist: isort>=6.0.0; extra == "dev"
Requires-Dist: pre-commit>=3.3.2; extra == "dev"
Requires-Dist: ruff>=0.5.0; extra == "dev"
Requires-Dist: commitizen>=4.4.0; extra == "dev"
Requires-Dist: twine>=6.0.0; extra == "dev"
Provides-Extra: docs
Requires-Dist: sphinx>=8.0.0; extra == "docs"
Requires-Dist: sphinx-rtd-theme>=3.0.0; extra == "docs"
Requires-Dist: myst-parser>=4.0.0; extra == "docs"
Dynamic: license-file
